{"resourceType":"StructureDefinition","url":"https://fhir.kbv.de/StructureDefinition/KBV_PR_MIO_TELE_PractitionerRole","version":"1.0.0","name":"KBV_PR_MIO_TELE_PractitionerRole","title":"KBV_PR_MIO_TELE_PractitionerRole","status":"active","publisher":"Kassenärztliche Bundesvereinigung (KBV)","description":"Dieses Profil bildet eine behandelnde Person/Einrichtung ab.","copyright":"Im folgenden Profil können Codes aus den Codesystemen Snomed, Loinc oder Ucum enthalten sein, die dem folgenden Urheberrecht unterliegen: This material includes SNOMED Clinical Terms® SNOMED CT® which is used by permission of SNOMED International. All rights reserved. SNOMED CT®, was originally created by The College of American Pathologists. SNOMED and SNOMED CT are registered trademarks of SNOMED International. Implementers of these artefacts must have the appropriate SNOMED CT Affiliate license. This material contains content from Loinc http://loinc.org. Loinc is copyright © 1995-2020, Regenstrief Institute, Inc. and the Logical Observation Identifiers Names and Codes Loinc Committee and is available at no cost under the license at http://loinc.org/license. Loinc® is a registered United States trademark of Regenstrief Institute, Inc. This product includes all or a portion of the UCUM table, UCUM codes, and UCUM definitions or is derived from it, subject to a license from Regenstrief Institute, Inc. and The UCUM Organization. Your use of the UCUM table, UCUM codes, UCUM definitions also is subject to this license, a copy of which is available at ​http://unitsofmeasure.org. The current complete UCUM table, UCUM Specification are available for download at ​http://unitsofmeasure.org. The UCUM table and UCUM codes are copyright © 1995-2009, Regenstrief Institute, Inc. and the Unified Codes for Units of Measures UCUM Organization. All rights reserved. THE UCUM TABLE IN ALL FORMATS, UCUM DEFINITIONS, AND SPECIFICATION ARE PROVIDED &quot;AS IS.&quot; ANY EXPRESS OR IMPLIED WARRANTIES ARE DISCLAIMED, INCLUDING, BUT NOT LIMITED TO, THE IMPLIED WARRANTIES OF MERCHANTABILITY AND FITNESS FOR A PARTICULAR PURPOSE.","fhirVersion":"4.0.1","kind":"resource","abstract":false,"type":"PractitionerRole","baseDefinition":"http://hl7.org/fhir/StructureDefinition/PractitionerRole","derivation":"constraint","differential":{"element":[{"id":"PractitionerRole","path":"PractitionerRole","definition":"Dieses Profil bildet eine behandelnde Person/Einrichtung ab."},{"id":"PractitionerRole.meta","path":"PractitionerRole.meta","min":1,"max":"1"},{"id":"PractitionerRole.meta.versionId","path":"PractitionerRole.meta.versionId","max":"0"},{"id":"PractitionerRole.meta.lastUpdated","path":"PractitionerRole.meta.lastUpdated","max":"0"},{"id":"PractitionerRole.meta.source","path":"PractitionerRole.meta.source","max":"0"},{"id":"PractitionerRole.meta.profile","path":"PractitionerRole.meta.profile","min":1,"max":"1","patternCanonical":"https://fhir.kbv.de/StructureDefinition/KBV_PR_MIO_TELE_PractitionerRole|1.0.0"},{"id":"PractitionerRole.meta.security","path":"PractitionerRole.meta.security","max":"0"},{"id":"PractitionerRole.meta.tag","path":"PractitionerRole.meta.tag","max":"0"},{"id":"PractitionerRole.implicitRules","path":"PractitionerRole.implicitRules","max":"0"},{"id":"PractitionerRole.language","path":"PractitionerRole.language","max":"0"},{"id":"PractitionerRole.text","path":"PractitionerRole.text","definition":"In diesem Element können die, in der Instanz, enthaltenen Informationen in einer menschenlesbaren Form zusammengefasst werden. Dabei ist zu beachten, dass keine Informationen aufgenommen werden dürfen, die nicht in strukturierter Form an anderer Stelle in der Instanz enthalten sind."},{"id":"PractitionerRole.text.status","path":"PractitionerRole.text.status","patternCode":"extensions"},{"id":"PractitionerRole.contained","path":"PractitionerRole.contained","max":"0"},{"id":"PractitionerRole.identifier","path":"PractitionerRole.identifier","max":"0"},{"id":"PractitionerRole.active","path":"PractitionerRole.active","max":"0"},{"id":"PractitionerRole.period","path":"PractitionerRole.period","max":"0"},{"id":"PractitionerRole.practitioner","path":"PractitionerRole.practitioner","min":1,"type":[{"code":"Reference","targetProfile":["https://fhir.kbv.de/StructureDefinition/KBV_PR_MIO_TELE_Practitioner|1.0.0"]}],"mustSupport":true},{"id":"PractitionerRole.practitioner.reference","path":"PractitionerRole.practitioner.reference","min":1,"mustSupport":true},{"id":"PractitionerRole.practitioner.type","path":"PractitionerRole.practitioner.type","max":"0"},{"id":"PractitionerRole.practitioner.identifier","path":"PractitionerRole.practitioner.identifier","max":"0"},{"id":"PractitionerRole.practitioner.display","path":"PractitionerRole.practitioner.display","max":"0"},{"id":"PractitionerRole.organization","path":"PractitionerRole.organization","min":1,"type":[{"code":"Reference","targetProfile":["https://fhir.kbv.de/StructureDefinition/KBV_PR_MIO_TELE_Organization|1.0.0"]}],"mustSupport":true},{"id":"PractitionerRole.organization.reference","path":"PractitionerRole.organization.reference","min":1,"mustSupport":true},{"id":"PractitionerRole.organization.type","path":"PractitionerRole.organization.type","max":"0"},{"id":"PractitionerRole.organization.identifier","path":"PractitionerRole.organization.identifier","max":"0"},{"id":"PractitionerRole.organization.display","path":"PractitionerRole.organization.display","max":"0"},{"id":"PractitionerRole.code","path":"PractitionerRole.code","mustSupport":true},{"id":"PractitionerRole.code.coding","path":"PractitionerRole.code.coding","slicing":{"discriminator":[{"type":"pattern","path":"$this"}],"rules":"open"},"mustSupport":true},{"id":"PractitionerRole.code.coding:rolleInEinrichtung","path":"PractitionerRole.code.coding","sliceName":"rolleInEinrichtung","min":1,"mustSupport":true,"binding":{"strength":"required","valueSet":"https://fhir.kbv.de/ValueSet/KBV_VS_MIO_TELE_Role_Care|1.0.0"}},{"id":"PractitionerRole.code.text","path":"PractitionerRole.code.text","mustSupport":true},{"id":"PractitionerRole.specialty","path":"PractitionerRole.specialty","mustSupport":true},{"id":"PractitionerRole.specialty.coding","path":"PractitionerRole.specialty.coding","slicing":{"discriminator":[{"type":"pattern","path":"$this"}],"rules":"open"},"mustSupport":true},{"id":"PractitionerRole.specialty.coding:kbvFachgruppencodierung","path":"PractitionerRole.specialty.coding","sliceName":"kbvFachgruppencodierung","min":1,"mustSupport":true,"binding":{"strength":"required","valueSet":"https://fhir.kbv.de/ValueSet/KBV_VS_SFHIR_BAR2_ARZTNRFACHGRUPPE|1.03"}},{"id":"PractitionerRole.specialty.text","path":"PractitionerRole.specialty.text","mustSupport":true},{"id":"PractitionerRole.location","path":"PractitionerRole.location","max":"0"},{"id":"PractitionerRole.healthcareService","path":"PractitionerRole.healthcareService","max":"0"},{"id":"PractitionerRole.telecom","path":"PractitionerRole.telecom","max":"0"},{"id":"PractitionerRole.availableTime","path":"PractitionerRole.availableTime","max":"0"},{"id":"PractitionerRole.notAvailable","path":"PractitionerRole.notAvailable","max":"0"},{"id":"PractitionerRole.availabilityExceptions","path":"PractitionerRole.availabilityExceptions","max":"0"},{"id":"PractitionerRole.endpoint","path":"PractitionerRole.endpoint","max":"0"}]}}